setup.py
pnr/__init__.py
pnr/auto.py
pnr.egg-info/PKG-INFO
pnr.egg-info/SOURCES.txt
pnr.egg-info/dependency_links.txt
pnr.egg-info/entry_points.txt
pnr.egg-info/not-zip-safe
pnr.egg-info/requires.txt
pnr.egg-info/top_level.txt