Metadata-Version: 1.0
Name: pnr
Version: 0.1
Summary: PNR CHECKER
Home-page: https://github.com/vikas-parashar/django-project-generator
Author: Akash Nimare
Author-email: svnitakash@gmai.com
License: MIT
Platform: UNKNOWN
